privhealth_lib/__init__.py
privhealth_lib/keycloak_module.py
privhealth_lib/oc_profiling.py
privhealth_lib/oc_transformation.py
privhealth_lib/oc_utils.py
privhealth_lib/oc_wrangling_and_cleaning.py
privhealth_lib-0.3.dist-info/LICENSE
privhealth_lib-0.3.dist-info/METADATA
privhealth_lib-0.3.dist-info/WHEEL
privhealth_lib-0.3.dist-info/top_level.txt
privhealth_lib-0.3.dist-info/RECORD
