Metadata-Version: 2.1
Name: privhealth_lib
Version: 0.3
Summary: PrivHealth Library
Home-page: https://github.com/macc-uece/privhealth-lib
Author: LASID Team
Classifier: Programming Language :: Python :: 3
Classifier: License :: OSI Approved :: MIT License
Classifier: Operating System :: OS Independent
Requires-Python: >=3.12
License-File: LICENSE
Requires-Dist: fastapi-keycloak
Requires-Dist: Pyjwt
Requires-Dist: requests
Requires-Dist: starlette
Requires-Dist: openclean
Requires-Dist: pandas
Requires-Dist: numpy
